dataverk_vault/__init__.py
dataverk_vault/api.py
dataverk_vault/connectors/__init__.py
dataverk_vault/connectors/vault.py
dataverk_vault/context/__init__.py
dataverk_vault/context/settings.py
dataverk_vault/exceptions/__init__.py
dataverk_vault/exceptions/exceptions.py
dataverk_vault/utils/__init__.py
dataverk_vault/utils/request_wrappers.py
dataverk_vault-0.1.10.dist-info/LICENSE
dataverk_vault-0.1.10.dist-info/METADATA
dataverk_vault-0.1.10.dist-info/WHEEL
dataverk_vault-0.1.10.dist-info/top_level.txt
dataverk_vault-0.1.10.dist-info/RECORD
