Metadata-Version: 2.1
Name: dataverk-vault
Version: 0.1.10
Summary: Vault integration for dataverk
Home-page: https://github.com/navikt
Author: NAV IKT
License: MIT
Keywords: vault dataverk
Platform: UNKNOWN
Requires-Python: >=3.6
License-File: LICENSE
Requires-Dist: backoff (>=1.10.0)
Requires-Dist: requests (>=2.23.0)
